delver_pdf-0.1.0.dist-info/METADATA
delver_pdf-0.1.0.dist-info/WHEEL
delver_pdf.libs/libgcc_s-39c9bb84.so.1
delver_pdf/__init__.py
delver_pdf/ffi.py
delver_pdf/libdelver_pdf.so
delver_pdf-0.1.0.dist-info/RECORD
