Metadata-Version: 2.4
Name: delver_pdf
Version: 0.1.0
Requires-Dist: maturin[zig]>=1.8.1
Requires-Dist: pymupdf>=1.25.2
Summary: Delver is a tool for declarative PDF extraction
Requires-Python: >=3.11
